README.md
setup.py
neuropipe/__init__.py
neuropipe/__main__.py
neuropipe/neuropipe.py
neuropipe.egg-info/PKG-INFO
neuropipe.egg-info/SOURCES.txt
neuropipe.egg-info/dependency_links.txt
neuropipe.egg-info/entry_points.txt
neuropipe.egg-info/requires.txt
neuropipe.egg-info/top_level.txt